interface/__init__.py
interface/cli_supervised.py
seldonian/__init__.py
seldonian/dataset.py
seldonian/seldonian_algorithm.py
seldonian/spec.py
test_engine-0.0.1.dist-info/LICENSE
test_engine-0.0.1.dist-info/METADATA
test_engine-0.0.1.dist-info/WHEEL
test_engine-0.0.1.dist-info/top_level.txt
test_engine-0.0.1.dist-info/RECORD
